canLogParse/__init__.py
canLogParse/parse.py
canLogParse/utils.py
canLogParse-1.0.3.dist-info/LICENSE
canLogParse-1.0.3.dist-info/METADATA
canLogParse-1.0.3.dist-info/WHEEL
canLogParse-1.0.3.dist-info/top_level.txt
canLogParse-1.0.3.dist-info/RECORD
