Metadata-Version: 2.1
Name: canLogParse
Version: 1.0.3
Summary: A tool to import and format data from Kvaser CAN files when you dont have a DBC file.
Home-page: https://github.com/hrjkknox/canLogParse
Author: Hamish Knox
Author-email: hrjkknox@gmail.com
License: UNKNOWN
Project-URL: Bug Tracker, https://github.com/hrjkknox/canLogParse/issues
Platform: UNKNOWN
Classifier: Programming Language :: Python :: 3
Classifier: License :: OSI Approved :: MIT License
Classifier: Operating System :: OS Independent
Requires-Python: >=3.6
License-File: LICENSE
